loggerpy/__init__.py
loggerpy/colors.py
loggerpy/logger_exception.py
loggerpy/tests/__init__.py
loggerpy/tests/test_loggerpy.py
loggerpy-2.1.1.dist-info/LICENSE.md
loggerpy-2.1.1.dist-info/METADATA
loggerpy-2.1.1.dist-info/WHEEL
loggerpy-2.1.1.dist-info/top_level.txt
loggerpy-2.1.1.dist-info/RECORD
