Metadata-Version: 2.1
Name: loggerpy
Version: 2.1.1
Summary: The simplest Python logger for everyday tasks.
Home-page: https://github.com/mett96/loggerpy
Author: Mattia Sanchioni
Author-email: mattia.sanchioni.dev@gmail.com
License: GPLv3
Keywords: logger log logging simple pylogger py-logger loggerpy logger-py simplelogger
Platform: UNKNOWN
Classifier: Development Status :: 5 - Production/Stable
Classifier: Programming Language :: Python :: 3
Classifier: Programming Language :: Python :: 3.6
Classifier: Programming Language :: Python :: 3.7
Classifier: Programming Language :: Python :: 3.8
Classifier: Programming Language :: Python :: 3.9
Classifier: License :: OSI Approved :: GNU General Public License v3 (GPLv3)
Classifier: Operating System :: OS Independent
Classifier: Intended Audience :: Developers
Classifier: Intended Audience :: Information Technology
Classifier: Topic :: Software Development :: Bug Tracking
Classifier: Topic :: Software Development :: Build Tools
